secretsweeper/__init__.py
secretsweeper/_core.abi3.so
secretsweeper/_core.pyi
secretsweeper-0.0.1a1.dist-info/METADATA
secretsweeper-0.0.1a1.dist-info/WHEEL
secretsweeper-0.0.1a1.dist-info/RECORD
secretsweeper-0.0.1a1.dist-info/licenses/LICENSE
