Metadata-Version: 2.4
Name: secretsweeper
Version: 0.0.1a1
Summary: Fast, in-memory secret-sanitizing CPython module written in Zig, designed for speed.
License-File: LICENSE
Author: Vitaliy Demidov
Author-email: notifications.recipient@gmail.com
Requires-Python: >=3.11
Classifier: Programming Language :: Python :: 3
Classifier: Programming Language :: Python :: 3.11
Classifier: Programming Language :: Python :: 3.12
Classifier: Programming Language :: Python :: 3.13
Classifier: Programming Language :: Python :: 3.14
